kotogram/__init__.py
kotogram/analysis.py
kotogram/augment.py
kotogram/cli.py
kotogram/constants.py
kotogram/evaluator.py
kotogram/exceptions.py
kotogram/japanese_parser.py
kotogram/kotogram.py
kotogram/locations.py
kotogram/model.py
kotogram/profile.py
kotogram/sudachi_japanese_parser.py
kotogram/validation.py
kotogram/model_data/__init__.py
kotogram/model_data/config.json
kotogram/model_data/labels.json
kotogram/model_data/model.pt
kotogram/model_data/model_type.txt
kotogram/model_data/tokenizer.json
kotogram-0.0.22.dist-info/licenses/LICENSE
kotogram-0.0.22.dist-info/METADATA
kotogram-0.0.22.dist-info/WHEEL
kotogram-0.0.22.dist-info/entry_points.txt
kotogram-0.0.22.dist-info/top_level.txt
kotogram-0.0.22.dist-info/RECORD
