Metadata-Version: 2.4
Name: kotogram
Version: 0.0.22
Summary: A dual Python/TypeScript library for Japanese text parsing and encoding using kotogram format
Author-email: Jomo Fisher <jomofisher@gmail.com>
Project-URL: Homepage, https://github.com/jomof/kotogram
Project-URL: Bug Reports, https://github.com/jomof/kotogram/issues
Project-URL: Source, https://github.com/jomof/kotogram
Keywords: japanese,nlp,sudachi,parser,tokenizer,kotogram
Classifier: Development Status :: 3 - Alpha
Classifier: Intended Audience :: Developers
Classifier: Programming Language :: Python :: 3
Classifier: Programming Language :: Python :: 3.9
Classifier: Programming Language :: Python :: 3.10
Classifier: Programming Language :: Python :: 3.11
Classifier: Programming Language :: Python :: 3.12
Classifier: Operating System :: OS Independent
Classifier: Topic :: Text Processing :: Linguistic
Classifier: Natural Language :: Japanese
Requires-Python: >=3.9
License-File: LICENSE
Requires-Dist: sudachipy
Requires-Dist: sudachidict-core
Requires-Dist: sudachidict-full
Requires-Dist: PyYaml
Requires-Dist: torch
Requires-Dist: rich
Dynamic: license-file
